legalesign/__init__.py
legalesign/_base_client.py
legalesign/_client.py
legalesign/_compat.py
legalesign/_constants.py
legalesign/_exceptions.py
legalesign/_files.py
legalesign/_models.py
legalesign/_qs.py
legalesign/_resource.py
legalesign/_response.py
legalesign/_streaming.py
legalesign/_types.py
legalesign/_version.py
legalesign/pagination.py
legalesign/py.typed
legalesign/_utils/__init__.py
legalesign/_utils/_compat.py
legalesign/_utils/_datetime_parse.py
legalesign/_utils/_logs.py
legalesign/_utils/_proxy.py
legalesign/_utils/_reflection.py
legalesign/_utils/_resources_proxy.py
legalesign/_utils/_streams.py
legalesign/_utils/_sync.py
legalesign/_utils/_transform.py
legalesign/_utils/_typing.py
legalesign/_utils/_utils.py
legalesign/lib/.keep
legalesign/resources/__init__.py
legalesign/resources/attachment.py
legalesign/resources/document.py
legalesign/resources/group.py
legalesign/resources/invited.py
legalesign/resources/member.py
legalesign/resources/notifications.py
legalesign/resources/pdf.py
legalesign/resources/signer.py
legalesign/resources/status.py
legalesign/resources/subscribe.py
legalesign/resources/template.py
legalesign/resources/unsubscribe.py
legalesign/resources/user.py
legalesign/resources/templatepdf/__init__.py
legalesign/resources/templatepdf/fields.py
legalesign/resources/templatepdf/templatepdf.py
legalesign/types/__init__.py
legalesign/types/attachment_list_params.py
legalesign/types/attachment_list_response.py
legalesign/types/attachment_response.py
legalesign/types/attachment_upload_params.py
legalesign/types/document_create_params.py
legalesign/types/document_create_response.py
legalesign/types/document_get_fields_response.py
legalesign/types/document_list_params.py
legalesign/types/document_list_response.py
legalesign/types/document_preview_params.py
legalesign/types/document_retrieve_response.py
legalesign/types/document_status_enum.py
legalesign/types/group_create_params.py
legalesign/types/group_list_params.py
legalesign-1.1.1.dist-info/METADATA
legalesign-1.1.1.dist-info/WHEEL
legalesign-1.1.1.dist-info/licenses/LICENSE
legalesign-1.1.1.dist-info/RECORD
